tacto/__init__.py
tacto/config_digit.yml
tacto/config_omnitact.yml
tacto/random_normal_generator.py
tacto/renderer.py
tacto/sensor.py
tacto/timeit.py
tacto-0.0.3.dist-info/LICENSE
tacto-0.0.3.dist-info/METADATA
tacto-0.0.3.dist-info/WHEEL
tacto-0.0.3.dist-info/top_level.txt
tacto-0.0.3.dist-info/RECORD
