Metadata-Version: 2.1
Name: tacto
Version: 0.0.3
Summary: Simulator for vision-based tactile sensors.
Home-page: https://github.com/facebookresearch/tacto
Author: Roberto Calandra
Author-email: rcalandra@fb.com
License: LICENSE
Keywords: science
Platform: UNKNOWN
Classifier: Programming Language :: Python :: 3
Classifier: Operating System :: POSIX :: Linux
Requires-Python: >=3.6
License-File: LICENSE
Requires-Dist: numpy (>=1.18.5)
Requires-Dist: pybullet (>=2.8.1)
Requires-Dist: matplotlib (>=3.1.3)
Requires-Dist: opencv-python (>=3.4.2.17)
Requires-Dist: omegaconf (>=2.0.6)
Requires-Dist: pyrender (>=0.1.43)
Requires-Dist: hydra-core (>=1.0.6)
Requires-Dist: urdfpy (>=0.0.22)
Requires-Dist: scipy
